Lab1/BcdToGrey/bcdToGrey.v
module bcdtogrey(A,e);
input [3:0]A;
output [3:0]e;


	xor g1(e[0],A[0],A[1]);
	xor g2(e[1],A[2],A[1]);
	or  g3(e[2],A[3],A[2]);
	buf b1 (e[3],A[3]);

endmodule

Lab1/BcdToGrey/tb_bcdToFrey.v
`include "bcdToGrey.v"

module tb_bcdToGrey();
	reg [3:0]A;
	wire [3:0]e;
	bcdtogrey btog(A,e);
	initial 
		begin
			$monitor(,$time," Input=%b , Output = %b ",A,e);
			#0 A=4'b0000;
			#5 A=4'b0001;
			#5 A=4'b0010;
			#5 A=4'b0011;
			#5 A=4'b0100;
			#5 A=4'b0101;
			#5 A=4'b0110;
			#5 A=4'b0111;
			#5 A=4'b1000;
			#5 A=4'b1001;
			
		end
	initial
		begin
		$dumpfile("out.vcd");
		$dumpvars;
		end

endmodule

Lab1/BcdToGrey/filename.vcd
$date
	Fri Aug 18 09:35:10 2017
$end
$version
	Icarus Verilog
$end
$timescale
	1s
$end
$scope module tb_bcdToGrey $end
$var wire 4 ! e [3:0] $end
$var reg 4 " A [3:0] $end
$scope module btog $end
$var wire 4 # A [3:0] $end
$var wire 4 $ e [3:0] $end
$upscope $end
$upscope $end
$enddefinitions $end
#0
$dumpvars
b0 $
b0 #
b0 "
b0 !
$end
#5
b1 !
b1 $
b1 "
b1 #
#10
b11 !
b11 $
b10 "
b10 #
#15
b10 !
b10 $
b11 "
b11 #
#20
b110 !
b110 $
b100 "
b100 #
#25
b111 !
b111 $
b101 "
b101 #
#30
b101 !
b101 $
b110 "
b110 #
#35
b100 !
b100 $
b111 "
b111 #
#40
b1100 !
b1100 $
b1000 "
b1000 #
#45
b1101 !
b1101 $
b1001 "
b1001 #
